setup.py
bench/__init__.py
bench_cxynb.egg-info/PKG-INFO
bench_cxynb.egg-info/SOURCES.txt
bench_cxynb.egg-info/dependency_links.txt
bench_cxynb.egg-info/entry_points.txt
bench_cxynb.egg-info/not-zip-safe
bench_cxynb.egg-info/requires.txt
bench_cxynb.egg-info/top_level.txt