Metadata-Version: 1.0
Name: bench-cxynb
Version: 5.0.0
Summary: Metadata driven, full-stack web framework
Home-page: UNKNOWN
Author: Frappe Technologies
Author-email: info@frappe.io
License: UNKNOWN
Platform: UNKNOWN
